setup.py
hotdoc_python_extension/VERSION.txt
hotdoc_python_extension/__init__.py
hotdoc_python_extension/python_doc_parser.py
hotdoc_python_extension/python_extension.py
hotdoc_python_extension/python_formatter.py
hotdoc_python_extension.egg-info/PKG-INFO
hotdoc_python_extension.egg-info/SOURCES.txt
hotdoc_python_extension.egg-info/dependency_links.txt
hotdoc_python_extension.egg-info/entry_points.txt
hotdoc_python_extension.egg-info/requires.txt
hotdoc_python_extension.egg-info/top_level.txt
hotdoc_python_extension/napoleon/__init__.py
hotdoc_python_extension/napoleon/docstring.py
hotdoc_python_extension/napoleon/iterators.py
hotdoc_python_extension/templates/__init__.py
hotdoc_python_extension/templates/python_class.html
hotdoc_python_extension/templates/python_prototype.html