Metadata-Version: 1.0
Name: hotdoc-python-extension
Version: 0.8.90
Summary: An extension for hotdoc that parses python using the jedi module and napoleon from sphinx
Home-page: https://github.com/hotdoc/hotdoc_python_extension
Author: Mathieu Duponchelle
Author-email: mathieu.duponchelle@opencreed.com
License: LGPLv2.1+
Keywords: python jed napoleon hotdoc
Platform: UNKNOWN
